covizpy/__init__.py
covizpy/get_data.py
covizpy/plot_metric.py
covizpy/plot_spec.py
covizpy/plot_summary.py
covizpy-1.0.24.dist-info/LICENSE
covizpy-1.0.24.dist-info/WHEEL
covizpy-1.0.24.dist-info/METADATA
covizpy-1.0.24.dist-info/RECORD
