Metadata-Version: 2.1
Name: covizpy
Version: 1.0.24
Summary: Provides access to Covid-19 data from Our World in Data, and functions to generate relevant charts and summaries.
Home-page: https://github.com/UBC-MDS/covizpy
License: MIT
Author: Rohit Rawat, Rong Li, Thomas Siu, Ting Zhe Yan
Requires-Python: >=3.9,<4.0
Classifier: License :: OSI Approved :: MIT License
Classifier: Programming Language :: Python :: 3
Classifier: Programming Language :: Python :: 3.10
Classifier: Programming Language :: Python :: 3.9
Requires-Dist: altair (>=4.2.0,<5.0.0)
Requires-Dist: altair-saver (>=0.5.0,<0.6.0)
Requires-Dist: pandas (>=1.3.5,<2.0.0)
Project-URL: Documentation, https://covizpy.readthedocs.io
Project-URL: Repository, https://github.com/UBC-MDS/covizpy
